spotii_notification_client/__init__.py
spotii_notification_client/api_client.py
spotii_notification_client/configuration.py
spotii_notification_client/rest.py
spotii_notification_client/notification/__init__.py
spotii_notification_client/notification/email_api.py
spotii_notification_client/notification/email_message.py
spotii_notification_client/notification/message.py
spotii_notification_client/notification/sms_api.py
spotii_notification_client/notification/sms_message.py
test/__init__.py
test/test_email_api.py
test/test_email_message.py
test/test_message.py
test/test_sms_api.py
test/test_sms_message.py
spotii_notification_client-1.0.5.dist-info/METADATA
spotii_notification_client-1.0.5.dist-info/WHEEL
spotii_notification_client-1.0.5.dist-info/top_level.txt
spotii_notification_client-1.0.5.dist-info/RECORD
