Metadata-Version: 2.1
Name: spotii-notification-client
Version: 1.0.5
Summary: Spotii Notification API
Home-page: https://www.spotii.me/
Author-email: hello@nuclearo.com
License: UNKNOWN
Keywords: Swagger,Spotii Notification API
Platform: UNKNOWN
Requires-Dist: urllib3 (>=1.15)
Requires-Dist: six (>=1.10)
Requires-Dist: certifi
Requires-Dist: python-dateutil
